note/cli.py
note/db_setup.py
note/display.py
note/helpers.py
note/main.py
note/note_crud.py
note/note_handler.py
note/reminder.py
note/reminder_crud.py
note/reminder_handler.py
note_shell-1.5.2.dist-info/METADATA
note_shell-1.5.2.dist-info/WHEEL
note_shell-1.5.2.dist-info/entry_points.txt
note_shell-1.5.2.dist-info/top_level.txt
note_shell-1.5.2.dist-info/RECORD
