Metadata-Version: 2.1
Name: note-shell
Version: 1.5.2
Summary: Command line tool for making notes
Home-page: https://github.com/nirabhratapaswi/nShells
Author: Nirabhra Tapaswi
Author-email: nirabhratapaswi@gmail.com
License: UNKNOWN
Platform: UNKNOWN
Classifier: Programming Language :: Python :: 3
Classifier: License :: OSI Approved :: MIT License
Classifier: Operating System :: OS Independent
Requires-Dist: readchar
Requires-Dist: tabulate
Requires-Dist: PyInquirer
Requires-Dist: pysqlite3
Requires-Dist: click
